cny/DataX.cp36-win_amd64.pyd
cny/DataX.cp39-win_amd64.pyd
cny/__init__.py
cny-1.0.5.dist-info/LICENSE
cny-1.0.5.dist-info/METADATA
cny-1.0.5.dist-info/WHEEL
cny-1.0.5.dist-info/top_level.txt
cny-1.0.5.dist-info/RECORD
