Metadata-Version: 2.1
Name: cny
Version: 1.0.5
Summary: cny公测工具包
Home-page: https://cns.ink/example
Author: rambo
Author-email: 6566666@qq.com
License: UNKNOWN
Platform: UNKNOWN
Classifier: Development Status :: 3 - Alpha
Classifier: Programming Language :: Python :: 3
Classifier: License :: OSI Approved :: MIT License
Classifier: Operating System :: Microsoft :: Windows
Requires-Python: >=3.6
